{"formJson":{"id":1,"uuid":"d742c480-06e4-414c-af4d-9196d77d1bb7","name":"Emergency Form","version":"1","published":true,"auditInfo":{"creator":{"uuid":"ba8ffc6b-bf03-11ea-8927-0242ac150003","display":"superman","links":[{"rel":"self","uri":"http://openmrs:8080/openmrs/ws/rest/v1/user/ba8ffc6b-bf03-11ea-8927-0242ac150003"}]},"dateCreated":"2020-07-05T21:36:59.000+0000","changedBy":{"uuid":"ba8ffc6b-bf03-11ea-8927-0242ac150003","display":"superman","links":[{"rel":"self","uri":"http://openmrs:8080/openmrs/ws/rest/v1/user/ba8ffc6b-bf03-11ea-8927-0242ac150003"}]},"dateChanged":"2020-07-05T21:37:49.000+0000"},"resources":[{"value":"{\"name\":\"Emergency Form\",\"id\":1,\"uuid\":\"d742c480-06e4-414c-af4d-9196d77d1bb7\",\"defaultLocale\":\"en\",\"controls\":[{\"type\":\"section\",\"label\":{\"translationKey\":\"SECTION_1\",\"type\":\"label\",\"value\":\"Prise en charge des urgences\",\"id\":\"1\"},\"properties\":{\"location\":{\"column\":0,\"row\":0}},\"id\":\"1\",\"controls\":[{\"type\":\"obsGroupControl\",\"label\":{\"translationKey\":\"EMERGENCY_FORM_2\",\"type\":\"label\",\"value\":\"Emergency Form\",\"id\":\"2\"},\"properties\":{\"addMore\":false,\"location\":{\"column\":0,\"row\":0}},\"id\":\"2\",\"concept\":{\"name\":\"Emergency Form\",\"uuid\":\"c47b5007-4ed6-1e55-215a-af7cbcb00329\",\"datatype\":\"N/A\",\"conceptClass\":\"ConvSet\",\"conceptHandler\":null,\"set\":true,\"setMembers\":[{\"name\":\"Hour\",\"uuid\":\"ca4a655a-8f16-53eb-0c0d-dbb6f58f3393\",\"datatype\":\"Text\",\"conceptClass\":\"Misc\",\"conceptHandler\":null,\"units\":null,\"hiNormal\":null,\"lowNormal\":null,\"hiAbsolute\":null,\"lowAbsolute\":null,\"answers\":[],\"properties\":{\"allowDecimal\":null}},{\"name\":\"Action taken\",\"uuid\":\"7d15e31b-021f-9f99-50e6-50ace62f3962\",\"datatype\":\"Text\",\"conceptClass\":\"Misc\",\"conceptHandler\":null,\"units\":null,\"hiNormal\":null,\"lowNormal\":null,\"hiAbsolute\":null,\"lowAbsolute\":null,\"answers\":[],\"properties\":{\"allowDecimal\":null}},{\"name\":\"Medication administered\",\"uuid\":\"6285ac8c-57e2-3190-7cf0-9e7773f522d0\",\"datatype\":\"Text\",\"conceptClass\":\"Misc\",\"conceptHandler\":null,\"units\":null,\"hiNormal\":null,\"lowNormal\":null,\"hiAbsolute\":null,\"lowAbsolute\":null,\"answers\":[],\"properties\":{\"allowDecimal\":null}},{\"name\":\"Patient status\",\"uuid\":\"014279e5-5a62-0b70-8105-a598bd6e483f\",\"datatype\":\"Text\",\"conceptClass\":\"Misc\",\"conceptHandler\":null,\"units\":null,\"hiNormal\":null,\"lowNormal\":null,\"hiAbsolute\":null,\"lowAbsolute\":null,\"answers\":[],\"properties\":{\"allowDecimal\":null}}]},\"controls\":[{\"type\":\"obsControl\",\"label\":{\"translationKey\":\"HOUR_3\",\"id\":\"3\",\"units\":\"\",\"type\":\"label\",\"value\":\"Hour\"},\"properties\":{\"mandatory\":false,\"notes\":false,\"addMore\":false,\"hideLabel\":false,\"controlEvent\":false,\"location\":{\"row\":0,\"column\":0}},\"id\":\"3\",\"concept\":{\"name\":\"Hour\",\"uuid\":\"ca4a655a-8f16-53eb-0c0d-dbb6f58f3393\",\"datatype\":\"Text\",\"conceptClass\":\"Misc\",\"conceptHandler\":null,\"units\":null,\"hiNormal\":null,\"lowNormal\":null,\"hiAbsolute\":null,\"lowAbsolute\":null,\"answers\":[],\"properties\":{\"allowDecimal\":null}},\"units\":null,\"hiNormal\":null,\"lowNormal\":null,\"hiAbsolute\":null,\"lowAbsolute\":null},{\"type\":\"obsControl\",\"label\":{\"translationKey\":\"ACTION_TAKEN_4\",\"id\":\"4\",\"units\":\"\",\"type\":\"label\",\"value\":\"Action taken\"},\"properties\":{\"mandatory\":false,\"notes\":false,\"addMore\":false,\"hideLabel\":false,\"controlEvent\":false,\"location\":{\"row\":1,\"column\":0}},\"id\":\"4\",\"concept\":{\"name\":\"Action taken\",\"uuid\":\"7d15e31b-021f-9f99-50e6-50ace62f3962\",\"datatype\":\"Text\",\"conceptClass\":\"Misc\",\"conceptHandler\":null,\"units\":null,\"hiNormal\":null,\"lowNormal\":null,\"hiAbsolute\":null,\"lowAbsolute\":null,\"answers\":[],\"properties\":{\"allowDecimal\":null}},\"units\":null,\"hiNormal\":null,\"lowNormal\":null,\"hiAbsolute\":null,\"lowAbsolute\":null},{\"type\":\"obsControl\",\"label\":{\"translationKey\":\"MEDICATION_ADMINISTERED_5\",\"id\":\"5\",\"units\":\"\",\"type\":\"label\",\"value\":\"Medication administered\"},\"properties\":{\"mandatory\":false,\"notes\":false,\"addMore\":false,\"hideLabel\":false,\"controlEvent\":false,\"location\":{\"row\":2,\"column\":0}},\"id\":\"5\",\"concept\":{\"name\":\"Medication administered\",\"uuid\":\"6285ac8c-57e2-3190-7cf0-9e7773f522d0\",\"datatype\":\"Text\",\"conceptClass\":\"Misc\",\"conceptHandler\":null,\"units\":null,\"hiNormal\":null,\"lowNormal\":null,\"hiAbsolute\":null,\"lowAbsolute\":null,\"answers\":[],\"properties\":{\"allowDecimal\":null}},\"units\":null,\"hiNormal\":null,\"lowNormal\":null,\"hiAbsolute\":null,\"lowAbsolute\":null},{\"type\":\"obsControl\",\"label\":{\"translationKey\":\"PATIENT_STATUS_6\",\"id\":\"6\",\"units\":\"\",\"type\":\"label\",\"value\":\"Patient status\"},\"properties\":{\"mandatory\":false,\"notes\":false,\"addMore\":false,\"hideLabel\":false,\"controlEvent\":false,\"location\":{\"row\":3,\"column\":0}},\"id\":\"6\",\"concept\":{\"name\":\"Patient status\",\"uuid\":\"014279e5-5a62-0b70-8105-a598bd6e483f\",\"datatype\":\"Text\",\"conceptClass\":\"Misc\",\"conceptHandler\":null,\"units\":null,\"hiNormal\":null,\"lowNormal\":null,\"hiAbsolute\":null,\"lowAbsolute\":null,\"answers\":[],\"properties\":{\"allowDecimal\":null}},\"units\":null,\"hiNormal\":null,\"lowNormal\":null,\"hiAbsolute\":null,\"lowAbsolute\":null}]}]}],\"events\":{},\"translationsUrl\":\"/openmrs/ws/rest/v1/bahmniie/form/translations\"}","dataType":"org.bahmni.customdatatype.datatype.FileSystemStorageDatatype","uuid":"e056e692-7e81-4c87-b07e-4dbfb65570aa"}]},"translations":[{"locale":"en","labels":{"SECTION_1":"Emergency management"},"concepts":{"ACTION_TAKEN_4":"Action taken","HOUR_3":"Hour","EMERGENCY_FORM_2":"Emergency Form","MEDICATION_ADMINISTERED_5":"Medication administered","PATIENT_STATUS_6":"Patient status"},"formName":"Emergency Form","version":"1","referenceVersion":null},{"locale":"fr","labels":{"SECTION_1":"Prise en charge des urgences"},"concepts":{"ACTION_TAKEN_4":"Action posée","HOUR_3":"Heure","EMERGENCY_FORM_2":"Formulaire d’ urgence","MEDICATION_ADMINISTERED_5":"Médication administrée","PATIENT_STATUS_6":"État du patient"},"formName":"Emergency Form","version":"1","referenceVersion":null}]}